fairlyuncertain/__init__.py
fairlyuncertain/benchmark.py
fairlyuncertain/utils.py
fairlyuncertain/visualize.py
fairlyuncertain/data/__init__.py
fairlyuncertain/data/acs_data.py
fairlyuncertain/data/aif360.py
fairlyuncertain/data/communities.py
fairlyuncertain/data/ihdp.py
fairlyuncertain/data/insurance.py
fairlyuncertain/data/twins.py
fairlyuncertain/methods/__init__.py
fairlyuncertain/methods/baseline.py
fairlyuncertain/methods/binomial_nll.py
fairlyuncertain/methods/ensemble.py
fairlyuncertain/methods/ft_transformer.py
fairlyuncertain/methods/model_nn.py
fairlyuncertain/methods/model_xgb.py
fairlyuncertain/methods/reductions.py
fairlyuncertain/methods/regression_nll.py
fairlyuncertain/methods/selective_ensemble.py
fairlyuncertain/methods/self_inconsistency.py
fairlyuncertain/methods/threshold.py
fairlyuncertain-0.0.4.dist-info/LICENSE
fairlyuncertain-0.0.4.dist-info/METADATA
fairlyuncertain-0.0.4.dist-info/WHEEL
fairlyuncertain-0.0.4.dist-info/top_level.txt
fairlyuncertain-0.0.4.dist-info/RECORD
