Metadata-Version: 2.1
Name: fairlyuncertain
Version: 0.0.4
Summary: Heteroscedastic uncertainty estimates for fair algorithms.
Home-page: https://github.com/rtealwitter/fairlyuncertain
Author: R. Teal Witter and Lucas Rosenblatt
Author-email: rtealwitter@gmail.com, lr2872@nyu.edu
Classifier: Programming Language :: Python :: 3
Classifier: License :: OSI Approved :: MIT License
Classifier: Operating System :: OS Independent
Requires-Python: >=3.6
License-File: LICENSE
Requires-Dist: numpy
Requires-Dist: torch
Requires-Dist: matplotlib
Requires-Dist: tqdm
Requires-Dist: pandas
Requires-Dist: aif360
Requires-Dist: scikit-learn
Requires-Dist: scipy
Requires-Dist: xgboost
Requires-Dist: ucimlrepo
Requires-Dist: fairlearn
Requires-Dist: folktables
Requires-Dist: requests
Requires-Dist: tab-transformer-pytorch
Requires-Dist: tabulate
